{
  "slug": "export-policy-documents",
  "name": "Export Policy Documents",
  "description": "Export policy documents from Progressive.",
  "type": "tool",
  "file": "export-policy-documents.ts",
  "app": "progressive",
  "inputSchema": [
    {
      "display_name": "policyId",
      "type": "string",
      "required": true,
      "description": "Policy identifier"
    },
    {
      "display_name": "documentType",
      "type": "string",
      "required": false,
      "description": "Document type filter"
    }
  ],
  "outputSchema": [
    {
      "display_name": "filePath",
      "type": "string",
      "required": true,
      "description": "Path to exported documents"
    },
    {
      "display_name": "documentCount",
      "type": "number",
      "required": true,
      "description": "Number of documents exported"
    },
    {
      "display_name": "success",
      "type": "boolean",
      "required": true,
      "description": "Whether export completed"
    }
  ],
  "tags": [
    "insurance",
    "auto",
    "export"
  ]
}
